m3_builder/__init__.py
m3_builder/build.py
m3_builder-1.2.0.dist-info/METADATA
m3_builder-1.2.0.dist-info/WHEEL
m3_builder-1.2.0.dist-info/entry_points.txt
m3_builder-1.2.0.dist-info/top_level.txt
m3_builder-1.2.0.dist-info/RECORD
