Metadata-Version: 2.1
Name: m3-builder
Version: 1.2.0
Summary: Сборщик пакетов
Home-page: https://stash.bars-open.ru/projects/EDUBASE/repos/utils
Author: BARS Group
Author-email: bars@bars-open.ru
Classifier: Intended Audience :: Developers
Classifier: Natural Language :: Russian
Classifier: Operating System :: POSIX
Classifier: Programming Language :: Python
Classifier: Programming Language :: Python :: 2
Classifier: Programming Language :: Python :: 2.7
Classifier: Programming Language :: Python :: 3
Classifier: Programming Language :: Python :: 3.6
Classifier: Development Status :: 5 - Production/Stable
Classifier: Topic :: Software Development
Classifier: Topic :: Software Development :: Build Tools
Requires-Dist: six
